{
    "type": "LazyLoad",
    "instanceId": "yui_3_8_1_1_1368422804894_52",
    "config": {},
    "assets": {
        "favicon.ico": "/favicon.ico"
    },
    "binders": {
        "index": "LazyLoadBinderIndex"
    },
    "langs": {},
    "models": {},
    "partials": {},
    "views": {
        "index": {
            "content-path": "/static/LazyLoad/views/index.hb.html",
            "engine": "hb"
        }
    },
    "controller": "LazyLoad",
    "acAddons": [
        "assets",
        "composite",
        "params"
    ],
    "assetsRoot": "/static/LazyLoad/assets",
    "defaults": {},
    "definition": {}
}